pytrackmate/__init__.py
pytrackmate/_trackmate.py
pytrackmate-1.3.4.dist-info/LICENSE
pytrackmate-1.3.4.dist-info/METADATA
pytrackmate-1.3.4.dist-info/WHEEL
pytrackmate-1.3.4.dist-info/top_level.txt
pytrackmate-1.3.4.dist-info/RECORD
