Metadata-Version: 2.2
Name: pytrackmate
Version: 1.3.4
Summary: Import Trackmate XML files in Python as Pandas dataframe.
Author-email: Hadrien Mary <hadrien.mary@gmail.com>
License: MIT License
Project-URL: homepage, https://github.com/hadim/pytrackmate
Classifier: License :: OSI Approved :: MIT License
Classifier: Programming Language :: Python :: 3
Classifier: Programming Language :: Python :: 3 :: Only
Classifier: Programming Language :: Python :: 3.10
Classifier: Programming Language :: Python :: 3.11
Classifier: Programming Language :: Python :: 3.12
Classifier: Programming Language :: Python :: 3.13
Classifier: Programming Language :: Python :: Implementation :: CPython
Classifier: Programming Language :: Python :: Implementation :: PyPy
Requires-Python: >=3.10
License-File: LICENSE
Requires-Dist: numpy
Requires-Dist: pandas
